shouldersurfscore/__init__.py
shouldersurfscore/analysis/breakin_analysis.py
shouldersurfscore/classes/__init__.py
shouldersurfscore/classes/attacker.py
shouldersurfscore/classes/bounds.py
shouldersurfscore/classes/device.py
shouldersurfscore/classes/gatekeeper.py
shouldersurfscore/classes/guess_manager.py
shouldersurfscore/classes/guessing_strategies.py
shouldersurfscore/classes/key.py
shouldersurfscore/classes/keyboard.py
shouldersurfscore/classes/keyplotter.py
shouldersurfscore/classes/keyrow.py
shouldersurfscore/classes/lab.py
shouldersurfscore/classes/password_rules.py
shouldersurfscore/classes/password_validator.py
shouldersurfscore/classes/point.py
shouldersurfscore/classes/timeouts.py
shouldersurfscore/defined_experiments/built_labs.py
shouldersurfscore/equipment/components.py
shouldersurfscore/equipment/devices.py
shouldersurfscore/traditional_metrics/__init__.py
shouldersurfscore/traditional_metrics/distances.py
shouldersurfscore-1.0.3.dist-info/licenses/LICENSE
shouldersurfscore-1.0.3.dist-info/METADATA
shouldersurfscore-1.0.3.dist-info/WHEEL
shouldersurfscore-1.0.3.dist-info/top_level.txt
shouldersurfscore-1.0.3.dist-info/RECORD
