Metadata-Version: 2.4
Name: shouldersurfscore
Version: 1.0.3
Summary: A python library intended to help researchers build more practical measures for shoulder surfing attack efficacy.
Author-email: "Business, Noneya" <skancertina@gmail.com>, tamsenam <tamsenam@pm.me>
License-Expression: GPL-3.0
Project-URL: Homepage, https://en.wikipedia.org/wiki/Scholarly_peer_review
Project-URL: Issues, https://en.wikipedia.org/wiki/Scholarly_peer_review
Classifier: Programming Language :: Python :: 3
Classifier: Operating System :: OS Independent
Requires-Python: >=3.10
License-File: LICENSE
Requires-Dist: noiftimer
Requires-Dist: typing_extensions
Requires-Dist: dacite
Requires-Dist: matplotlib
Dynamic: license-file
